motevowrapper/__init__.py
motevowrapper/__main__.py
motevowrapper/_version.py
motevowrapper/motevowrapper.py
motevowrapper-0.0.6.dist-info/LICENSE.txt
motevowrapper-0.0.6.dist-info/METADATA
motevowrapper-0.0.6.dist-info/WHEEL
motevowrapper-0.0.6.dist-info/top_level.txt
motevowrapper-0.0.6.dist-info/RECORD
