Metadata-Version: 2.1
Name: motevowrapper
Version: 0.0.6
Summary: Simple Python MotEvo wrapper.
Home-page: https://github.com/brlauuu/motevowrapper
Author: Đorđe Relić
Author-email: dorde.relic@protonmail.com
License: MIT
Download-URL: https://github.com/brlauuu/motevowrapper/archive/v0.0.6.tar.gz
Keywords: MotEvo,wrapper,binding,sites,tfbs-discovery
Platform: UNKNOWN
Classifier: Development Status :: 5 - Production/Stable
Classifier: Intended Audience :: Science/Research
Classifier: Topic :: Scientific/Engineering :: Bio-Informatics
Classifier: License :: OSI Approved :: MIT License
Classifier: Programming Language :: Python :: 3
Requires-Dist: pandas
